README.md
setup.py
lao_test.egg-info/PKG-INFO
lao_test.egg-info/SOURCES.txt
lao_test.egg-info/dependency_links.txt
lao_test.egg-info/top_level.txt
winshang_test/__init__.py
winshang_test/crawler.py