Metadata-Version: 2.1
Name: lao-test
Version: 1.1.0
Summary: PyPI Tutorial
Home-page: https://github.com/
Author: jianling
Author-email: laojianling@winshang.com
License: UNKNOWN
Platform: UNKNOWN
Classifier: Programming Language :: Python :: 3
Classifier: License :: OSI Approved :: MIT License
Classifier: Operating System :: OS Independent
